etcetra/__init__.py
etcetra/client.py
etcetra/errors.py
etcetra/py.typed
etcetra/types.py
etcetra/grpc_api/__init__.py
etcetra/grpc_api/annotations_pb2.py
etcetra/grpc_api/annotations_pb2_grpc.py
etcetra/grpc_api/auth_pb2.py
etcetra/grpc_api/auth_pb2_grpc.py
etcetra/grpc_api/code_pb2.py
etcetra/grpc_api/code_pb2_grpc.py
etcetra/grpc_api/error_details_pb2.py
etcetra/grpc_api/error_details_pb2_grpc.py
etcetra/grpc_api/etcdserver_pb2.py
etcetra/grpc_api/etcdserver_pb2_grpc.py
etcetra/grpc_api/gogo_pb2.py
etcetra/grpc_api/gogo_pb2_grpc.py
etcetra/grpc_api/http_pb2.py
etcetra/grpc_api/http_pb2_grpc.py
etcetra/grpc_api/httpbody_pb2.py
etcetra/grpc_api/httpbody_pb2_grpc.py
etcetra/grpc_api/kv_pb2.py
etcetra/grpc_api/kv_pb2_grpc.py
etcetra/grpc_api/membership_pb2.py
etcetra/grpc_api/membership_pb2_grpc.py
etcetra/grpc_api/raft_internal_pb2.py
etcetra/grpc_api/raft_internal_pb2_grpc.py
etcetra/grpc_api/rpc_pb2.py
etcetra/grpc_api/rpc_pb2_grpc.py
etcetra/grpc_api/snap_pb2.py
etcetra/grpc_api/snap_pb2_grpc.py
etcetra/grpc_api/status_pb2.py
etcetra/grpc_api/status_pb2_grpc.py
etcetra/grpc_api/v3election_pb2.py
etcetra/grpc_api/v3election_pb2_grpc.py
etcetra/grpc_api/v3lock_pb2.py
etcetra/grpc_api/v3lock_pb2_grpc.py
etcetra-0.1.19.dist-info/LICENSE
etcetra-0.1.19.dist-info/METADATA
etcetra-0.1.19.dist-info/WHEEL
etcetra-0.1.19.dist-info/top_level.txt
etcetra-0.1.19.dist-info/RECORD
