Metadata-Version: 2.1
Name: etcetra
Version: 0.1.19
Summary: Etcd client built with pure asyncio gRPC library
Home-page: https://github.com/lablup/etcetra
Author: Lablup Inc.
Author-email: kyujin.cho@lablup.com
License: Apache License 2.0
Project-URL: Documentation, https://github.com/lablup/etcetra/blob/main/docs/references.md
Project-URL: Source, https://github.com/lablup/etcetra
Project-URL: Tracker, https://github.com/lablup/etcetra/issues
Classifier: Development Status :: 4 - Beta
Classifier: License :: OSI Approved :: Apache Software License
Classifier: Intended Audience :: Developers
Classifier: Programming Language :: Python
Classifier: Programming Language :: Python :: 3
Classifier: Programming Language :: Python :: 3.10
Classifier: Programming Language :: Python :: 3.11
Classifier: Programming Language :: Python :: 3.12
Classifier: Operating System :: POSIX
Classifier: Operating System :: MacOS :: MacOS X
Classifier: Topic :: Software Development
Requires-Python: >=3.10
License-File: LICENSE
Requires-Dist: protobuf ~=4.25.3
Requires-Dist: grpcio ==1.62.2
Requires-Dist: grpcio-tools ==1.62.2
Provides-Extra: build
Requires-Dist: wheel >=0.36.2 ; extra == 'build'
Requires-Dist: twine >=3.4.1 ; extra == 'build'
Provides-Extra: dev
Provides-Extra: lint
Requires-Dist: flake8 >=4.0.1 ; extra == 'lint'
Requires-Dist: flake8-commas >=2.1 ; extra == 'lint'
Provides-Extra: test
Requires-Dist: pytest ~=6.2.5 ; extra == 'test'
Requires-Dist: pytest-asyncio ~=0.16.0 ; extra == 'test'
Requires-Dist: pytest-cov >=2.11 ; extra == 'test'
Requires-Dist: pytest-mock >=3.5.0 ; extra == 'test'
Requires-Dist: codecov ; extra == 'test'
Provides-Extra: typecheck
Requires-Dist: mypy >=1.4.1 ; extra == 'typecheck'
Requires-Dist: types-protobuf ; extra == 'typecheck'
Requires-Dist: types-setuptools ; extra == 'typecheck'
